[
    {
        "src": "/assets/lab-photo/2025.PNG",
        "alt": "Lab photo 2025",
        "caption": "PEACH Lab members, summer 2025."
    },
    {
        "src": "/assets/lab-photo/2024.jpg",
        "alt": "Lab photo 2024",
        "caption": "PEACH Lab members, summer 2024."
    },
    {
        "src": "/assets/lab-photo/CHI25.png",
        "alt": "Lab photo 2025",
        "caption": "PEACH Lab members, CHI 2025."
    },
    {
        "src": "/assets/lab-photo/teaching.png",
        "alt": "Lab photo 2025",
        "caption": "PEACH Lab members, teaching 2025."
    },
    {
        "src": "/assets/lab-photo/2024-2.jpg",
        "alt": "Lab photo 2024",
        "caption": "PEACH Lab members, summer excursion 2024."
    }
]